goodreads_mcp/__init__.py
goodreads_mcp/cli.py
goodreads_mcp-0.1.3.dist-info/METADATA
goodreads_mcp-0.1.3.dist-info/WHEEL
goodreads_mcp-0.1.3.dist-info/entry_points.txt
goodreads_mcp-0.1.3.dist-info/licenses/LICENSE
goodreads_mcp-0.1.3.dist-info/RECORD
