Metadata-Version: 2.4
Name: goodreads-mcp
Version: 0.1.3
Summary: A CLI tool for Goodreads MCP integration
Project-URL: Homepage, https://github.com/gather-engineering/goodreads-mcp
Project-URL: Repository, https://github.com/gather-engineering/goodreads-mcp
Project-URL: Issues, https://github.com/gather-engineering/goodreads-mcp/issues
Author-email: faisal burhanudin <faisalburhanudiN@gmail.com>
License: MIT
License-File: LICENSE
Keywords: cli,goodreads,mcp
Classifier: Development Status :: 3 - Alpha
Classifier: Intended Audience :: Developers
Classifier: License :: OSI Approved :: MIT License
Classifier: Programming Language :: Python :: 3
Classifier: Programming Language :: Python :: 3.13
Requires-Python: >=3.13
Requires-Dist: fastmcp>=2.10.2
Requires-Dist: requests
